{"category":"","exampleCount":71,"vocabCount":590,"wordCount":1470,"wordlist":{"1":14,"2":1,"3":1,"12":4,"21":2,"48":1,"100":1,"200":4,"224":1,"500":1,"8900":1,"12000":1,"40000":1,"rt":43,"@apollocurrency:":2,"check":3,"out":4,"our":4,"latest":2,"blog":2,"post!":2,"in":26,"case":3,"you":5,"missed":3,"it.":2,"":161,"\n\n\"about":2,"apollo":2,"tax":2,"system\"…":2,"$mara":2,".45":2,"red":2,"to":34,"green":2,"#blockchain":7,"is":8,"hot!\n\nchart":2,"\n8":2,"into":5,"ma":2,"cross":5,"triggered":2,"starter":2,".435":2,"\n\nlook":2,"for":5,"the":18,"continu…":2,"https://t.co/nrwwe0om6l":2,"@lip_smak:":1,"[sold]\nlady":1,"with":12,"an":1,"ermine":1,"2020\n\nover":1,"@blockchainartex":1,"\n\n#cryptoart":1,"#blockchainart":1,"https://t.co/xcpv7ef8ko":1,"@phliz2017:":3,"earn":4,"$btc":18,"while":3,"browsing":3,"#browser.\n\n#btc":3,"#bitcoin":9,"#eth":4,"$eth":6,"#ethereum":7,"#cryptotrading":3,"#crypto":7,"#cryptocurrency":3,"#cryptocu…":3,"@tecnicohectorj:":1,"@rcnfinance":1,"@ripioapp":1,"we":6,"will":8,"projects":1,"that":6,"create":1,"solutions":1,"like":1,"that.":1,"can":6,"support":1,"@rcnfinan…":1,"@mertiumfin:":1,"how":3,"#emergingtechnologies":1,"are":2,"impacting":1,"industries:":1,"https://t.co/upnhmhtmqf":1,"\nty":1,"@kirkdborne\n———————\n#bigdata":1,"#datascience":1,"#…":1,"@kydcoin:":1,"pleased":1,"announce":1,"$kydc":2,"now":1,"available":1,"as":4,"faucet":1,"on":11,"@stakecube":1,"platform.":1,"\n\nclaim":1,"your":1,"first":1,"today\n":1,"https…":1,"@bloxlivetv:":1,"this":8,"week":1,"by":3,"@coinfieldex:\n\n-":1,"jumps":1,"above":2,"$8,000,":1,"reversing":1,"march":1,"crash\n-":1,"china’s":1,"regulator":1,"approves":1,"b…":1,"@ripple:":2,"learn":2,"@forteplatform":2,"leverages":2,"@interledger":2,"#ilp":2,"arm":2,"#devs":2,"tools":2,"integrate":2,"technology":2,"gamin…":2,"@cryptoomist:":1,"look":2,"idea.":2,"be":4,"a":10,"part":2,"of":18,"amazing":2,"project":2,"us.":2,"anybody":2,"have":2,"opportunity":2,"take":2,"advantage":2,"enormous":1,"p…":1,"eno…":1,"https://t.co/t5a5i2fjms":1,"@egretia_io:":1,"#egt":1,"#giveaways!":1,"#internationalworkersday":1,"\none":1,"person":1,"gets":3,"20000egt\n✅like":1,"&amp;":12,"retweet":1,"\n✅follow":1,"@egretia_io\n✅tag":1,"fr…":1,"#arcs":1,"#arx":1,"#kucoin":1,"https://t.co/fdzthsrdrn":1,"@mmcrypto":1,"@peterschiff":1,"i":2,"wonder":1,"if":2,"or":6,"when":2,"peter":1,"fold":1,"subject":1,"@ighatav:":2,"yes":2,"market":4,"going":3,"up\netherium":2,"goin":2,"up\nbitcoin":2,"also\n#bitcoin\n#etherium\n\n@cctip_io":2,"airdrop":2,"nfx":2,"https://t.co/k9qxna9fkx":2,"@jgproduct:":1,"interview":1,"@gladstein":1,"yesterday":1,"catch":1,"it":1,"below":1,"discussed":1,"#bitcoin,":1,"human":1,"rights,":1,"fi…":1,"＃btc":2,"＃bitcoin":2,"＃比特币":2,"https://t.co/1mkbt0gvdr":1,"@irishgirlcrypt1:":2,"i'll":2,"give":2,"someone":2,"who":2,"retweets":2,"tweet":2,"$5":2,"$trx":2,"hours.":2,"must":2,"following":2,"me":3,"@fiatearthmaps":2,"\n\n🍀good":2,"l…":2,"usd":1,"before":2,"halving!":1,"@bitcoinomist:":1,"celebrate":1,"upward":1,"move":1,"am":1,"giving":1,"away":1,"#trx":1,"\n\n★follow":1,"+":3,"retweet\n★tag":1,"\n\nwinner":1,"hours":1,"🚀":3,"good":3,"luc…":1,"@cryptorambler:":2,"🚨#bitcoin":2,"#giveaway🚨\n\n🎁three":2,"persons":2,"$50":2,"🤑\n\n🧜‍♀️rules:\n\n✅like":2,"retweet\n\n✅follow":2,"@coindcx":2,"and":4,"me\n\n⏰…":2,"@cryptocom:":4,"#halving":2,"affect":2,"price":11,"time?\nguess":2,"btc/usdt":2,"halving":4,"day":2,"12:00:00":2,"utc":2,"right":2,"win":2,"whole":2,"$btc…":2,"https://t.co/t5qzhcea66":1,"etc":12,"usd:":6,"$6.46":2,"(change:":12,"+1.1":2,"%)\nprice":6,"btc:":6,"0.00074564":2,"ƀ":6,"-0.37":2,"%)\n#ethereumclassic":6,"#etc":6,"$etc":8,"@sonnenshein":1,"#ethereumclassic":4,"work":1,"just":1,"fine":1,"@tenaciousdragon:":2,"since":2,"#bitcoin is":2,"spotlight":2,"today,":2,"it’s":2,"time":2,"remind":2,"devs:\n\nyou":2,"use":2,"#bitcoin +":2,"#ethere…":2,"$6.39":1,"-1.24":1,"0.00074841":1,"+0.58":1,"@saturnprotocol:":2,"chain":3,"atomic":4,"swaps!":3,"happy":3,"confirm":3,"saturn":3,"protocol":3,"v2":3,"allow":3,"users":3,"enjoy":3,"decentralized":3,"trading":2,"betw…":2,"仮想通貨でスポーツベットやカジノを楽しむなら、1xbetがおすすめです。取扱通貨は、#bitcoin":1,"#btc":2,"#monero":1,"#zcash":1,"#dogecoin…":1,"https://t.co/yb7snyta3e":1,"$6.47":1,"-0.15":2,"0.00074407":1,"+0.55":1,"@cryptolydian:":1,"#saturnprotocol":1,"allows":1,"swap":1,"between":1,"#ethereum,":1,"https://t.co/px86kqcvxa":1,"trading…":1,"https://t.co/hojmjptbby":1,"$6.48":1,"-1.67":1,"0.00073999":1,"-0.73":1,"@eth_classic:":2,"monetary":1,"policy":1,"establishes":1,"came":1,"being":1,"deal":1,"long":1,"history":1,"inflationary":1,"mo…":1,"these":1,"live":1,"games":1,"#ethereumclassic,":1,"plugged":1,"directly":1,"@commonwealthgg":1,"ecosystem!":1,"$6.59":1,"0.00074544":1,"+0.17":1,"top":1,"volume":1,"gainers":1,"past":1,"hour":1,"(top":1,"cap)":1,"$usdc":1,"$ckb":1,"$bnb":1,"$zil":3,"https://t.co/7daadbxhll":1,"🔄":6,"prices":6,"update":6,"$usd":3,"(1":6,"hour):\n\n$eos":5,"-":18,"2.82":1,"$":13,"(+0.57":1,"%)\n$dash":2,"81.94":1,"(+1.0":1,"%)\n$xlm":2,"0.07":2,"(+1.43…":1,"https://t.co/eenyhgqb7v":1,"increased!":1,"buying":1,"@":2,"$8662.7":2,"selling":1,"$neo":1,"$dgb":1,"$dash":1,"$strat":1,"$eos":1,"$omg":1,"$pay":1,"$xrp":1,"$xmr":1,"$gas":1,"😆":1,"$eur":1,"2.59":1,"€":3,"(+1.97":1,"%)\n$iot":2,"0.16":1,"(+2.32":1,"%)\n$etc":3,"5.93":1,"(…":1,"https://t.co/uwhnkxyd7s":1,"2.83":2,"(+2.13":1,"0.18":1,"(+2.6":1,"%)":1,"\n$etc":1,"6.5":1,"$…":2,"https://t.co/0nqqcl6wog":1,"$usdt":2,"(+1.72":1,"%)\n$ada":1,"0.05":2,"(+1.71":1,"6.48":1,"(+1.99":1,"%…":1,"https://t.co/zacx9s8qvf":1,"hour):\n\n$ada":1,"(+1.44":1,"%)\n$neo":1,"8.96":1,"(+2.79":1,"6.43":1,"https://t.co/8x5kgxu93l":1,"@ipred_x:":2,"all":2,"eyes":2,"$sierra":2,"#sierracoin":2,"\n\n$1":2,"soon!":2,"\n\n$btc":2,"$wrx":2,"$xtz":2,"$dgtx":2,"$ogn":2,"$ocean":2,"$icon":2,"$coti":2,"$stx":2,"$qnt":2,"$link":2,"$band":2,"$x…":2,"@cryptoexp38560a:":1,"$aion":1,"target":1,"hit!":1,"35%":1,"profit🔥💥\n\nfor":1,"more":1,"free":2,"signals,":1,"join":1,"https://t.co/jsy2k31wqm\n\n$go":1,"$knc":1,"$nebl":1,"$poly":1,"#cryptocurre…":1,"new":1,"listing:\nbitcoin":1,"station":1,"https://t.co/llmslbatvd\n\ncheck":1,"program":1,"status":1,"at":2,"monitor":1,"invest:…":1,"https://t.co/h2qryfuqsu":1,"2.81":1,"(-0.63":1,"81.13":1,"(-1.05":1,"(-1.5…":1,"https://t.co/xcgvxhy4uy":1,"@scotttrxwarrior:":3,"🔥":3,"ledger":3,"nano":3,"s":3,"wallet":3,"#giveaway":3,"🔥\n\n💰winner":3,"may":5,"also":3,"choose":3,"$65":3,"$eth\n\nrules\n1.":3,"follow":3,"@klaytncommunity":3,"me…":3,"presenting":2,"https://t.co/vcnztabjog":4,"special,":2,"50%":2,"off":2,"exchange-$1m":2,"a…":2,"@george1trader:":1,"$btc\n\nthis":1,"ranging":1,"until":1,"close":1,"weekly":1,"11.8k.":1,"that's":1,"real":1,"firework":1,"starts!":1,"https://t.co/m…":1,"@nuls":1,"@bitcoin":1,"@nerve_network":1,"@nguyenthao9222\n@joselinebermeo\nnulsd6hgb5j8ezpcrguxnouxvshebu3j1fk59\n$btc":1,"9303$":1,"was":1,"corrected":1,"technical":1,"level.":1,"it's":1,"rock":1,"solid":1,"far":1,"trend":1,"concerned.\n\nattached":1,"sample":1,"screenshots…":1,"https://t.co/hnnvxbz3ax":1,"@idealfog:":1,"✅download":1,"quicrypto":1,"app":1,":":1,"https://t.co/tdtdxhp9ir":1,"\nto":1,"$nano":1,"watching":1,"videos":1,"installing":1,"apps.\n\n✅each…":1,"@bitcoinagile:":1,"hit":1,"$10k":1,"within":1,"next":1,"year???":1,"coinbase:ethusd":1,"moon333":1,"https://t.co/lcjhdg9cmd":1,"https://t.…":1,"@satoshiflipper:":1,"hold":1,"here,":1,"build":1,"range":1,"8900-9400":1,"area":1,"perhaps":1,"mini":1,"alt":1,"season":1,"process.":1,"h…":1}}